cli/__init__.py
cli/cli.py
cli/shell_utils.py
cli/commands/__init__.py
cli/commands/init.py
cli/commands/query.py
cli/commands/shell.py
cli/commands/update.py
sql_agent_tool/__init__.py
sql_agent_tool/config.py
sql_agent_tool/core.py
sql_agent_tool/exceptions.py
sql_agent_tool/models.py
sql_agent_tool/utils.py
sql_agent_tool/llm/__init__.py
sql_agent_tool/llm/base.py
sql_agent_tool/llm/deepseek.py
sql_agent_tool/llm/factory.py
sql_agent_tool/llm/gemini.py
sql_agent_tool/llm/groq.py
sql_agent_tool/llm/openai.py
sql_agent_tool-0.1.9.dist-info/licenses/LICENSE
sql_agent_tool-0.1.9.dist-info/licenses/NOTICE
tests/__init__.py
tests/test_core.py
tests/test_gemini_llm.py
tests/test_postgresql.py
tests/test_sql_agent.py
sql_agent_tool-0.1.9.dist-info/METADATA
sql_agent_tool-0.1.9.dist-info/WHEEL
sql_agent_tool-0.1.9.dist-info/entry_points.txt
sql_agent_tool-0.1.9.dist-info/top_level.txt
sql_agent_tool-0.1.9.dist-info/RECORD
