Metadata-Version: 2.4
Name: sql-agent-tool
Version: 0.1.9
Summary: A secure SQL tool for AI agents to interact with databases
Home-page: https://github.com/Dadiya-Harsh/sql-tool
Author: Harsh Dadiya
Author-email: Harsh Dadiya <harshdadiya@gmail.com>
License: Apache-2.0
Project-URL: Homepage, https://github.com/Dadiya-Harsh/sql-tool
Project-URL: Repository, https://github.com/Dadiya-Harsh/sql-tool
Project-URL: Bug Tracker, https://github.com/Dadiya-Harsh/sql-tool/issues
Classifier: Programming Language :: Python :: 3
Classifier: Operating System :: OS Independent
Requires-Python: >=3.10
License-File: LICENSE
License-File: NOTICE
Requires-Dist: sqlalchemy>=2.0
Requires-Dist: psycopg2-binary>=2.9
Requires-Dist: groq>=0.1
Requires-Dist: pydantic>=2.0
Requires-Dist: sqlparse>=0.4
Requires-Dist: python-dotenv>=0.20
Requires-Dist: openai>=1.0
Requires-Dist: google-generativeai>=0.3
Requires-Dist: click>=8.1.7
Requires-Dist: pyyaml>=6.0
Provides-Extra: dev
Requires-Dist: pytest>=7.0; extra == "dev"
Requires-Dist: pytest-mock>=3.0; extra == "dev"
Requires-Dist: black>=23.0; extra == "dev"
Requires-Dist: flake8>=6.0; extra == "dev"
Dynamic: author
Dynamic: home-page
Dynamic: license-file
Dynamic: requires-python
